Workbook

Sheet Setup
A1: Content Creator Revenue Tracker — Setup
A3: Parameter
A4: Currency Symbol | B4: $ | C4: Change to your local currency (e.g., £, €, ¥)
A5: Tax Rate (%) | B5: 25 | C5: Estimated effective tax rate for income estimation
A6: Platform 1 | B6: YouTube AdSense | C6: Primary video platform revenue
A7: Platform 2 | B7: Sponsorships | C7: Brand deal income
A8: Platform 3 | B8: Patreon/Memberships | C8: Recurring membership revenue
A9: Platform 4 | B9: Affiliate Income | C9: Commission from affiliate links
A10: Platform 5 | B10: Digital Products | C10: Ebooks, templates, courses
A11: Platform 6 | B11: Merchandise | C11: Physical product sales
A12: Platform 7 | B12: Consulting/Coaching | C12: 1-on-1 or group consulting fees
A13: Platform 8 | B13: Speaking Events | C13: Paid speaking, podcasts, panels
A14: Platform 9 | B14: Donations/Tips | C14: Super Chat, Ko-fi, Buy Me a Coffee
A15: Platform 10 | B15: Other Income | C15: Any other creator income
A16: Revenue Categories
A17: This template tracks 10 income streams across all creator platforms.

Sheet Income
A1: Income Tracker — Log Every Payment
A2: Date | B2: Platform | C2: Income Type | D2: Client/Source | E2: Description | F2: Amount | G2: Tax Deductible? | H2: Payment Status | I2: Invoice # | J2: Quarter | K2: Month | L2: Notes
A3: 2026-01-15 | B3: YouTube AdSense | C3: Ad Revenue | D3: YouTube | E3: January AdSense payout | F3: 1250 | G3: TRUE | H3: Paid | J3: Q1 | K3: January
A4: 2026-01-20 | B4: Sponsorships | C4: Brand Deal | D4: TechCorp Inc | E4: Product review video sponsorship | F4: 3000 | G4: TRUE | H4: Paid | I4: INV-001 | J4: Q1 | K4: January | L4: Includes usage rights
A5: 2026-02-01 | B5: Patreon/Memberships | C5: Monthly Recurring | D5: Patreon | E5: February membership revenue (150 members) | F5: 750 | G5: FALSE | H5: Paid | J5: Q1 | K5: February
A6: 2026-02-10 | B6: Affiliate Income | C6: Commission | D6: Amazon Associates | E6: January affiliate commissions | F6: 420 | G6: FALSE | H6: Paid | J6: Q1 | K6: February
A7: 2026-02-15 | B7: Digital Products | C7: Product Sales | D7: Gumroad | E7: Spreadsheet template bundle sales | F7: 890 | G7: TRUE | H7: Paid | J7: Q1 | K7: February
A8: 2026-03-01 | B8: YouTube AdSense | C8: Ad Revenue | D8: YouTube | E8: February AdSense payout | F8: 1380 | G8: TRUE | H8: Paid | J8: Q1 | K8: March
A9: 2026-03-05 | B9: Sponsorships | C9: Brand Deal | D9: SkillShare | E9: Course sponsorship + affiliate | F9: 2500 | G9: TRUE | H9: Pending | I9: INV-002 | J9: Q1 | K9: March | L9: Net 30 terms
A10: 2026-03-15 | B10: Merchandise | C10: Product Sales | D10: Print-on-demand | E10: T-shirt and mug sales | F10: 340 | G10: TRUE | H10: Paid | J10: Q1 | K10: March
A11: 2026-04-01 | B11: Patreon/Memberships | C11: Monthly Recurring | D11: Patreon | E11: March membership (162 members) | F11: 810 | G11: FALSE | H11: Paid | J11: Q2 | K11: April | L11: 12 new members
A12: 2026-04-10 | B12: Consulting/Coaching | C12: 1-on-1 Session | D12: Private client | E12: 2-hour strategy session | F12: 500 | G12: TRUE | H12: Paid | I12: INV-003 | J12: Q2 | K12: April
A64: TOTALS | F64: =SUM(F3:F62)

Sheet Expenses
A1: Expense Tracker — Track All Business Expenses
A2: Date | B2: Category | C2: Sub-Category | D2: Vendor/Payee | E2: Description | F2: Amount | G2: Tax Deductible? | H2: Receipt Saved? | I2: Quarter | J2: Month | K2: Notes
A3: 2026-01-05 | B3: Software/Subscriptions | C3: Video Editing | D3: Adobe Creative Cloud | E3: Monthly Creative Cloud subscription | F3: 54.99 | G3: TRUE | H3: TRUE | I3: Q1 | J3: January
A4: 2026-01-10 | B4: Equipment | C4: Camera Gear | D4: B&H Photo | E4: New microphone and lighting kit | F4: 350 | G4: TRUE | H4: TRUE | I4: Q1 | J4: January | K4: Depreciable asset
A5: 2026-01-15 | B5: Home Office | C5: Internet | D5: ISP Provider | E5: Monthly broadband internet | F5: 89.99 | G5: TRUE | H5: TRUE | I5: Q1 | J5: January | K5: 60% business use
A6: 2026-02-01 | B6: Software/Subscriptions | C6: Analytics | D6: TubeBuddy/VidIQ | E6: YouTube optimization tool | F6: 15 | G6: TRUE | H6: TRUE | I6: Q1 | J6: February
A7: 2026-02-05 | B7: Content Production | C7: Stock Media | D7: Envato Elements | E7: Stock footage and music license | F7: 29 | G7: TRUE | H7: TRUE | I7: Q1 | J7: February
A8: 2026-02-15 | B8: Marketing/Advertising | C8: Social Ads | D8: Meta Ads | E8: Instagram promotion for new video series | F8: 150 | G8: TRUE | H8: TRUE | I8: Q1 | J8: February
A9: 2026-03-01 | B9: Platform Fees | C9: Payment Processing | D9: Stripe/PayPal | E9: Transaction fees on product sales | F9: 45 | G9: TRUE | H9: TRUE | I9: Q1 | J9: March
A10: 2026-03-10 | B10: Education/Training | C10: Online Course | D10: MasterClass | E10: Filmmaking course subscription | F10: 180 | G10: TRUE | H10: TRUE | I10: Q1 | J10: March | K10: Annual subscription
A11: 2026-03-20 | B11: Travel | C11: Event Travel | D11: Flight booking | E11: Flight to CreatorCon conference | F11: 450 | G11: TRUE | H11: TRUE | I11: Q1 | J11: March
A12: 2026-04-01 | B12: Software/Subscriptions | C12: Design Tool | D12: Canva Pro | E12: Monthly Canva Pro subscription | F12: 12.99 | G12: TRUE | H12: TRUE | I12: Q2 | J12: April
A64: TOTALS | F64: =SUM(F3:F62)

Sheet Dashboard
A1: Creator Revenue Dashboard
A2: All metrics auto-calculate from Income and Expenses sheets
B4: Total Revenue | C4: =Income!F64 | D4: Total Expenses | E4: =Expenses!F64 | F4: Net Profit | G4: =C4-E4 | H4: Profit Margin | I4: =IF(C4=0,0,G4/C4)
B6: Est. Quarterly Tax | C6: =ROUND((C4-E4)*Setup!B5,0) | D6: After-Tax Income | E6: =C4-E4-C6 | F6: Avg Monthly Income | G6: =C4/12 | H6: Income Streams | I6: =COUNTA(Income!B3:B62)
B9: Revenue by Platform | D9: Monthly Revenue Trend | G9: Expense Breakdown
B10: Platform | C10: Total Income | D10: % of Total
B11: ='Setup!B6' | C11: =SUMIF(Income!B$3:B$62,B11,Income!F$3:F$62) | D11: =IF(C11=0,0,C11/C11)
B12: ='Setup!B7' | C12: =SUMIF(Income!B$3:B$62,B12,Income!F$3:F$62) | D12: =IF(C11=0,0,C12/C11)
B13: ='Setup!B8' | C13: =SUMIF(Income!B$3:B$62,B13,Income!F$3:F$62) | D13: =IF(C11=0,0,C13/C11)
B14: ='Setup!B9' | C14: =SUMIF(Income!B$3:B$62,B14,Income!F$3:F$62) | D14: =IF(C11=0,0,C14/C11)
B15: ='Setup!B10' | C15: =SUMIF(Income!B$3:B$62,B15,Income!F$3:F$62) | D15: =IF(C11=0,0,C15/C11)
B16: ='Setup!B11' | C16: =SUMIF(Income!B$3:B$62,B16,Income!F$3:F$62) | D16: =IF(C11=0,0,C16/C11)
B17: ='Setup!B12' | C17: =SUMIF(Income!B$3:B$62,B17,Income!F$3:F$62) | D17: =IF(C11=0,0,C17/C11)
B18: ='Setup!B13' | C18: =SUMIF(Income!B$3:B$62,B18,Income!F$3:F$62) | D18: =IF(C11=0,0,C18/C11)
B19: ='Setup!B14' | C19: =SUMIF(Income!B$3:B$62,B19,Income!F$3:F$62) | D19: =IF(C11=0,0,C19/C11)
B20: ='Setup!B15' | C20: =SUMIF(Income!B$3:B$62,B20,Income!F$3:F$62) | D20: =IF(C11=0,0,C20/C11)
B23: Quarterly Tax Schedule
B24: Quarter | C24: Est. Income | D24: Est. Tax Due | E24: Paid?
B25: Q1 | C25: =SUMIF(Income!J$3:J$62,B25,Income!F$3:F$62) | D25: =ROUND(C25*Setup!B5,0)
B26: Q2 | C26: =SUMIF(Income!J$3:J$62,B26,Income!F$3:F$62) | D26: =ROUND(C26*Setup!B5,0)
B27: Q3 | C27: =SUMIF(Income!J$3:J$62,B27,Income!F$3:F$62) | D27: =ROUND(C27*Setup!B5,0)
B28: Q4 | C28: =SUMIF(Income!J$3:J$62,B28,Income!F$3:F$62) | D28: =ROUND(C28*Setup!B5,0)
B32: Key Creator Metrics
B33: Avg Revenue per Stream | C33: =IF(I6=0,0,B4/I6)
B34: Top Platform (by Revenue) | C34: =INDEX(B11:B20,MAX(MATCH(MAX(C11:C20),C11:C20,0)),1)
B35: Total Deductible Expenses | C35: =SUMIF(Expenses!G$3:G$62,TRUE,Expenses!F$3:F$62)
B36: Non-Deductible Expenses | C36: =SUMIF(Expenses!G$3:G$62,FALSE,Expenses!F$3:F$62)
B37: Revenue per Month (Avg) | C37: =B4/COUNTA(Income!K$3:K$62)
B40: Tip: Update Income and Expenses sheets regularly. Dashboard auto-calculates.
